docs/Makefile
docs/changelog.rst
docs/conf.py
docs/index.rst
docs/requirements.txt
docs/api/exceptions.rst
docs/api/index.rst
docs/api/schema.rst
docs/api/testing/checks.rst
docs/api/testing/filesystem.rst
docs/api/testing/index.rst
docs/api/testing/util.rst
jscc/__init__.py
jscc/exceptions.py
jscc/schema.py
jscc/testing/__init__.py
jscc/testing/checks.py
jscc/testing/filesystem.py
jscc/testing/util.py
jscc-0.3.0.dist-info/LICENSE
jscc-0.3.0.dist-info/METADATA
jscc-0.3.0.dist-info/WHEEL
jscc-0.3.0.dist-info/top_level.txt
jscc-0.3.0.dist-info/RECORD
