Metadata-Version: 2.1
Name: jscc
Version: 0.3.0
Summary: Tools for data standards that use JSON Schema and CSV codelists
Author-email: Open Contracting Partnership and Open Data Services Co-operative Limited <data@open-contracting.org>
License: BSD
Project-URL: Homepage, https://github.com/open-contracting/jscc
Classifier: License :: OSI Approved :: BSD License
Classifier: Operating System :: OS Independent
Classifier: Programming Language :: Python :: 3.9
Classifier: Programming Language :: Python :: 3.10
Classifier: Programming Language :: Python :: 3.11
Classifier: Programming Language :: Python :: 3.12
Classifier: Programming Language :: Python :: Implementation :: CPython
Classifier: Programming Language :: Python :: Implementation :: PyPy
License-File: LICENSE
Requires-Dist: json-merge-patch
Requires-Dist: jsonref >=1
Requires-Dist: requests
Provides-Extra: test
Requires-Dist: coverage ; extra == 'test'
Requires-Dist: jsonschema ; extra == 'test'
Requires-Dist: pytest ; extra == 'test'
Requires-Dist: pytest-recording ; extra == 'test'
